{
    "asset": {
        "generatetool": "kara",
        "gltfUpAxis": "Z",
        "version": "0.0"
    },
    "geometricError": 0.9375,
    "root": {
        "boundingVolume": {
            "sphere": [
                -2414112.3229080965,
                5389661.690291845,
                2401141.211779533,
                15.02751350402832
            ]
        },
        "children": null,
        "content": {
            "uri": "Tile_208_090_L21_00000013.b3dm"
        },
        "geometricError": 0.9375,
        "refine": "REPLACE"
    }
}
