{
    "asset": {
        "generatetool": "kara",
        "gltfUpAxis": "Z",
        "version": "0.0"
    },
    "geometricError": 0.9375,
    "root": {
        "boundingVolume": {
            "sphere": [
                -2413960.8100754945,
                5389964.511315532,
                2400600.968781117,
                13.700194358825684
            ]
        },
        "children": null,
        "content": {
            "uri": "Tile_206_086_L21_00000121.b3dm"
        },
        "geometricError": 0.9375,
        "refine": "REPLACE"
    }
}
