{
    "asset": {
        "generatetool": "kara",
        "gltfUpAxis": "Z",
        "version": "0.0"
    },
    "geometricError": 0.9375,
    "root": {
        "boundingVolume": {
            "sphere": [
                -2413847.7681662343,
                5389804.882654042,
                2401069.833080644,
                13.700194358825684
            ]
        },
        "children": null,
        "content": {
            "uri": "Tile_206_089_L21_00000213.b3dm"
        },
        "geometricError": 0.9375,
        "refine": "REPLACE"
    }
}
