{
    "asset": {
        "generatetool": "kara",
        "gltfUpAxis": "Z",
        "version": "0.0"
    },
    "geometricError": 0.9375,
    "root": {
        "boundingVolume": {
            "sphere": [
                -2413931.177078924,
                5389806.635433777,
                2400982.6303889123,
                13.523417472839355
            ]
        },
        "children": null,
        "content": {
            "uri": "Tile_206_089_L21_00000111.b3dm"
        },
        "geometricError": 0.9375,
        "refine": "REPLACE"
    }
}
