{
    "asset": {
        "generatetool": "kara",
        "gltfUpAxis": "Z",
        "version": "0.0"
    },
    "geometricError": 1.875,
    "root": {
        "boundingVolume": {
            "sphere": [
                -2414034.0768997422,
                5389627.689118025,
                2401376.80499765,
                11.588923454284668
            ]
        },
        "children": [
            {
                "boundingVolume": {
                    "sphere": [
                        -2414034.0768997422,
                        5389627.689118025,
                        2401376.80499765,
                        11.588922500610352
                    ]
                },
                "content": {
                    "uri": "Tile_208_091_L21_00000220.json"
                },
                "geometricError": 0.9375,
                "refine": "REPLACE"
            }
        ],
        "content": {
            "uri": "Tile_208_091_L20_0000022.b3dm"
        },
        "geometricError": 1.875,
        "refine": "REPLACE"
    }
}
