{
    "asset": {
        "generatetool": "kara",
        "gltfUpAxis": "Z",
        "version": "0.0"
    },
    "geometricError": 3.75,
    "root": {
        "boundingVolume": {
            "sphere": [
                -2414097.7113368833,
                5389635.198144575,
                2401419.5801162757,
                14.27856159210205
            ]
        },
        "children": [
            {
                "boundingVolume": {
                    "sphere": [
                        -2414097.5277486844,
                        5389635.280403243,
                        2401419.580056554,
                        15.267422676086426
                    ]
                },
                "content": {
                    "uri": "Tile_208_091_L20_0000040.json"
                },
                "geometricError": 1.875,
                "refine": "REPLACE"
            }
        ],
        "content": {
            "uri": "Tile_208_091_L19_000004.b3dm"
        },
        "geometricError": 3.75,
        "refine": "REPLACE"
    }
}
