{
    "asset": {
        "generatetool": "kara",
        "gltfUpAxis": "Z",
        "version": "0.0"
    },
    "geometricError": 1.875,
    "root": {
        "boundingVolume": {
            "sphere": [
                -2414230.3491713614,
                5389855.452545674,
                2400574.952125989,
                26.971778869628906
            ]
        },
        "children": [
            {
                "boundingVolume": {
                    "sphere": [
                        -2414223.1976687214,
                        5389862.565830188,
                        2400566.232043338,
                        13.612092971801758
                    ]
                },
                "content": {
                    "uri": "Tile_208_086_L21_00000100.json"
                },
                "geometricError": 0.9375,
                "refine": "REPLACE"
            },
            {
                "boundingVolume": {
                    "sphere": [
                        -2414240.422615956,
                        5389854.847915563,
                        2400566.237610251,
                        13.612092971801758
                    ]
                },
                "content": {
                    "uri": "Tile_208_086_L21_00000101.json"
                },
                "geometricError": 0.9375,
                "refine": "REPLACE"
            },
            {
                "boundingVolume": {
                    "sphere": [
                        -2414220.2893488174,
                        5389856.087518985,
                        2400583.585287661,
                        13.700194358825684
                    ]
                },
                "content": {
                    "uri": "Tile_208_086_L21_00000102.json"
                },
                "geometricError": 0.9375,
                "refine": "REPLACE"
            },
            {
                "boundingVolume": {
                    "sphere": [
                        -2414237.5142960465,
                        5389848.369604343,
                        2400583.5908546154,
                        13.700194358825684
                    ]
                },
                "content": {
                    "uri": "Tile_208_086_L21_00000103.json"
                },
                "geometricError": 0.9375,
                "refine": "REPLACE"
            }
        ],
        "content": {
            "uri": "Tile_208_086_L20_0000010.b3dm"
        },
        "geometricError": 1.875,
        "refine": "REPLACE"
    }
}
