{
    "asset": {
        "generatetool": "kara",
        "gltfUpAxis": "Z",
        "version": "0.0"
    },
    "geometricError": 0.9375,
    "root": {
        "boundingVolume": {
            "sphere": [
                -2414293.023008512,
                5389651.865030099,
                2400985.495894691,
                13.893572807312012
            ]
        },
        "children": null,
        "content": {
            "uri": "Tile_209_089_L21_00000100.b3dm"
        },
        "geometricError": 0.9375,
        "refine": "REPLACE"
    }
}
