{
    "asset": {
        "generatetool": "kara",
        "gltfUpAxis": "Z",
        "version": "0.0"
    },
    "geometricError": 0.9375,
    "root": {
        "boundingVolume": {
            "sphere": [
                -2413841.835221756,
                5390157.918475512,
                2400288.432222704,
                13.612092971801758
            ]
        },
        "children": null,
        "content": {
            "uri": "Tile_205_084_L21_00000011.b3dm"
        },
        "geometricError": 0.9375,
        "refine": "REPLACE"
    }
}
