{
    "asset": {
        "generatetool": "kara",
        "gltfUpAxis": "Z",
        "version": "0.0"
    },
    "geometricError": 0.9375,
    "root": {
        "boundingVolume": {
            "sphere": [
                -2414321.8173990324,
                5389566.9178815745,
                2401307.7686220626,
                11.201900482177734
            ]
        },
        "children": null,
        "content": {
            "uri": "Tile_209_091_L21_00000141.b3dm"
        },
        "geometricError": 0.9375,
        "refine": "REPLACE"
    }
}
