{
    "asset": {
        "generatetool": "kara",
        "gltfUpAxis": "Z",
        "version": "0.0"
    },
    "geometricError": 0.9375,
    "root": {
        "boundingVolume": {
            "sphere": [
                -2414185.060614843,
                5389549.648017618,
                2401334.8317068624,
                15.726391792297363
            ]
        },
        "children": null,
        "content": {
            "uri": "Tile_209_091_L21_00000201.b3dm"
        },
        "geometricError": 0.9375,
        "refine": "REPLACE"
    }
}
