{
    "asset": {
        "generatetool": "kara",
        "gltfUpAxis": "Z",
        "version": "0.0"
    },
    "geometricError": 0.9375,
    "root": {
        "boundingVolume": {
            "sphere": [
                -2414161.1369319935,
                5389952.621728253,
                2400427.3774466654,
                13.523417472839355
            ]
        },
        "children": null,
        "content": {
            "uri": "Tile_207_085_L21_00000111.b3dm"
        },
        "geometricError": 0.9375,
        "refine": "REPLACE"
    }
}
