{
    "asset": {
        "generatetool": "kara",
        "gltfUpAxis": "Z",
        "version": "0.0"
    },
    "geometricError": 1.875,
    "root": {
        "boundingVolume": {
            "sphere": [
                -2414139.3875147877,
                5389927.170324791,
                2400505.8697086466,
                26.97246551513672
            ]
        },
        "children": [
            {
                "boundingVolume": {
                    "sphere": [
                        -2414132.335034754,
                        5389934.246661855,
                        2400497.132380618,
                        13.700194358825684
                    ]
                },
                "content": {
                    "uri": "Tile_207_085_L21_00000310.json"
                },
                "geometricError": 0.9375,
                "refine": "REPLACE"
            },
            {
                "boundingVolume": {
                    "sphere": [
                        -2414149.446034117,
                        5389926.580138162,
                        2400497.138035487,
                        13.612092971801758
                    ]
                },
                "content": {
                    "uri": "Tile_207_085_L21_00000311.json"
                },
                "geometricError": 0.9375,
                "refine": "REPLACE"
            },
            {
                "boundingVolume": {
                    "sphere": [
                        -2414129.407410174,
                        5389927.725349299,
                        2400514.6013969895,
                        13.700194358825684
                    ]
                },
                "content": {
                    "uri": "Tile_207_085_L21_00000312.json"
                },
                "geometricError": 0.9375,
                "refine": "REPLACE"
            },
            {
                "boundingVolume": {
                    "sphere": [
                        -2414146.5184095292,
                        5389920.058825589,
                        2400514.607051901,
                        13.612092971801758
                    ]
                },
                "content": {
                    "uri": "Tile_207_085_L21_00000313.json"
                },
                "geometricError": 0.9375,
                "refine": "REPLACE"
            }
        ],
        "content": {
            "uri": "Tile_207_085_L20_0000031.b3dm"
        },
        "geometricError": 1.875,
        "refine": "REPLACE"
    }
}
