{
    "asset": {
        "generatetool": "kara",
        "gltfUpAxis": "Z",
        "version": "0.0"
    },
    "geometricError": 1.875,
    "root": {
        "boundingVolume": {
            "sphere": [
                -2414145.242721383,
                5389940.212855098,
                2400470.931633331,
                26.97246551513672
            ]
        },
        "children": [
            {
                "boundingVolume": {
                    "sphere": [
                        -2414138.190220057,
                        5389947.289144736,
                        2400462.19428408,
                        13.700194358825684
                    ]
                },
                "content": {
                    "uri": "Tile_207_085_L21_00000130.json"
                },
                "geometricError": 0.9375,
                "refine": "REPLACE"
            },
            {
                "boundingVolume": {
                    "sphere": [
                        -2414155.3012194317,
                        5389939.622621074,
                        2400462.199938863,
                        13.612092971801758
                    ]
                },
                "content": {
                    "uri": "Tile_207_085_L21_00000131.json"
                },
                "geometricError": 0.9375,
                "refine": "REPLACE"
            },
            {
                "boundingVolume": {
                    "sphere": [
                        -2414135.2626380483,
                        5389940.767927001,
                        2400479.663342981,
                        13.700194358825684
                    ]
                },
                "content": {
                    "uri": "Tile_207_085_L21_00000132.json"
                },
                "geometricError": 0.9375,
                "refine": "REPLACE"
            },
            {
                "boundingVolume": {
                    "sphere": [
                        -2414152.373637418,
                        5389933.101403324,
                        2400479.668997807,
                        13.612092971801758
                    ]
                },
                "content": {
                    "uri": "Tile_207_085_L21_00000133.json"
                },
                "geometricError": 0.9375,
                "refine": "REPLACE"
            }
        ],
        "content": {
            "uri": "Tile_207_085_L20_0000013.b3dm"
        },
        "geometricError": 1.875,
        "refine": "REPLACE"
    }
}
