{
    "asset": {
        "generatetool": "kara",
        "gltfUpAxis": "Z",
        "version": "0.0"
    },
    "geometricError": 1.875,
    "root": {
        "boundingVolume": {
            "sphere": [
                -2414321.7246167613,
                5389592.913084831,
                2401179.8180582183,
                25.895076751708984
            ]
        },
        "children": [
            {
                "boundingVolume": {
                    "sphere": [
                        -2414315.1066718823,
                        5389597.676479473,
                        2401175.8075089324,
                        7.866729736328125
                    ]
                },
                "content": {
                    "uri": "Tile_209_090_L21_00000140.json"
                },
                "geometricError": 0.9375,
                "refine": "REPLACE"
            },
            {
                "boundingVolume": {
                    "sphere": [
                        -2414329.2662343755,
                        5389594.737665619,
                        2401168.2179207415,
                        10.102032661437988
                    ]
                },
                "content": {
                    "uri": "Tile_209_090_L21_00000141.json"
                },
                "geometricError": 0.9375,
                "refine": "REPLACE"
            },
            {
                "boundingVolume": {
                    "sphere": [
                        -2414311.0383050004,
                        5389593.206633822,
                        2401189.83640586,
                        10.226038932800293
                    ]
                },
                "content": {
                    "uri": "Tile_209_090_L21_00000142.json"
                },
                "geometricError": 0.9375,
                "refine": "REPLACE"
            },
            {
                "boundingVolume": {
                    "sphere": [
                        -2414328.452096604,
                        5389584.940973595,
                        2401190.873089514,
                        10.695728302001953
                    ]
                },
                "content": {
                    "uri": "Tile_209_090_L21_00000143.json"
                },
                "geometricError": 0.9375,
                "refine": "REPLACE"
            }
        ],
        "content": {
            "uri": "Tile_209_090_L20_0000014.b3dm"
        },
        "geometricError": 1.875,
        "refine": "REPLACE"
    }
}
