{
    "asset": {
        "generatetool": "kara",
        "gltfUpAxis": "Z",
        "version": "0.0"
    },
    "geometricError": 0.9375,
    "root": {
        "boundingVolume": {
            "sphere": [
                -2414275.4303335324,
                5389612.922267759,
                2401137.6885088542,
                10.553667068481445
            ]
        },
        "children": null,
        "content": {
            "uri": "Tile_209_090_L21_00000104.b3dm"
        },
        "geometricError": 0.9375,
        "refine": "REPLACE"
    }
}
