{
    "asset": {
        "generatetool": "kara",
        "gltfUpAxis": "Z",
        "version": "0.0"
    },
    "geometricError": 1.875,
    "root": {
        "boundingVolume": {
            "sphere": [
                -2413819.6821872424,
                5390039.442401144,
                2400574.8133948063,
                26.971778869628906
            ]
        },
        "children": [
            {
                "boundingVolume": {
                    "sphere": [
                        -2413812.5304332757,
                        5390046.555123087,
                        2400566.0930606057,
                        13.612092971801758
                    ]
                },
                "content": {
                    "uri": "Tile_205_086_L21_00000100.json"
                },
                "geometricError": 0.9375,
                "refine": "REPLACE"
            },
            {
                "boundingVolume": {
                    "sphere": [
                        -2413829.75588302,
                        5390038.838333201,
                        2400566.099131655,
                        13.612092971801758
                    ]
                },
                "content": {
                    "uri": "Tile_205_086_L21_00000101.json"
                },
                "geometricError": 0.9375,
                "refine": "REPLACE"
            },
            {
                "boundingVolume": {
                    "sphere": [
                        -2413809.6221135184,
                        5390040.076812284,
                        2400583.4463038947,
                        13.700194358825684
                    ]
                },
                "content": {
                    "uri": "Tile_205_086_L21_00000102.json"
                },
                "geometricError": 0.9375,
                "refine": "REPLACE"
            },
            {
                "boundingVolume": {
                    "sphere": [
                        -2413826.8475632556,
                        5390032.360022381,
                        2400583.452374988,
                        13.700194358825684
                    ]
                },
                "content": {
                    "uri": "Tile_205_086_L21_00000103.json"
                },
                "geometricError": 0.9375,
                "refine": "REPLACE"
            }
        ],
        "content": {
            "uri": "Tile_205_086_L20_0000010.b3dm"
        },
        "geometricError": 1.875,
        "refine": "REPLACE"
    }
}
